check_pip_compile/__init__.py
check_pip_compile/__main__.py
check_pip_compile/_version.py
check_pip_compile/cli.py
check_pip_compile-0.1.1.dist-info/METADATA
check_pip_compile-0.1.1.dist-info/WHEEL
check_pip_compile-0.1.1.dist-info/entry_points.txt
check_pip_compile-0.1.1.dist-info/top_level.txt
check_pip_compile-0.1.1.dist-info/RECORD
